Workbook

Sheet Plan Cost
B2: PLAN COST | G3 DT
B7: NUM D'OFERTA | I7: NUM INF
B8: CLIENT / UBICACIÓ OBRA | J8: BCN
B9: DESCRIPCIÓ TITÒL | E9: EG HAB UNIF RUBI
B10: TIPUS | E10: Exploratory characterization studies.
B11: CENTRE COST | E11: Cataluña
B13: Persona Contacte | J13: RESUM
B14: Telèfon de Contacte | J14: NET VALUE | M14: =+(E36+E47+F65+E52)-(E36+E47+F65+E52)*G19 -> 669.1
B15: Mobil de Contacte | J15: TOTAL COST | M15: =+E36+E47+E52+E65*61.4 -> 667.9
B16: e-mail de Contacte | J16: MARGIN | M16: =+(M21-M15)/M21 -> 0.20488095
J17: HOURS | M17: =+E65 -> 5
B18: Assignació kilometratge (EUR / km) | G18: 0.19 | J18: SAP CTRL | M18: =IFERROR(IF(F65/E65>=40,(F65)/40,E65),0) -> 7.705
B19: Descompte comercial (%) | G19: 0 | J19: SUBCONTRACTING | M19: =+E36+E52 -> 360.9
J20: TRAVEL EXPENSES | M20: =+E47 -> 0
B21: Tecnic responsable | E21: Eva Vázquez Marcet | J21: OFFER AMOUNT | M21: =OFERTA!H70 -> 840
B23: Subcontracting | I23: Comments
B24: sondejos | E24: =OFERTA!H24 -> 325.9
B25: Calicates | E25: =OFERTA!H55 -> 0
B26: laboratori | E26: =OFERTA!H49 -> 35
B27: laboratorio 2
B28: Tasas
B29: <<otros>>
B30: Tubería PVC
B31: Arquetes
B32: Retirada residuos
B33: <<otros>>
B34: <<otros>>
B35: <<otros>>
B36: IMPORT TOTAL € | E36: =SUM(E24:G35) -> 360.9
B38: Travel expenses | I38: Comments
B39: Combustible | E39: =OFERTA!H66 -> 0 | I39: Km (9 litros/100 Km) = l * 1,80 €
B40: Peatjes
B41: Tren/avió/lloguer cotxes
B42: Hotel | E42: =OFERTA!L66 -> 0
B43: Esmorzar/dinar/sopar | E43: =OFERTA!I66+OFERTA!J66+OFERTA!K66 -> 0
B44: Despeses varies
B45: <<otros>>
B46: <<otros>>
B47: IMPORT TOTAL € | E47: =SUM(E39:G46) -> 0
B49: Internal subcontracting | I49: Comments
B50: Lab. Valdemoro
B51: <<otros>>
B52: TOTAL AMOUNT (€) | E52: =SUM(E50:G51) -> 0
B53: Hours foreseen por project
E54: Hours | F54: €/h
B55: Desplçaments
B56: Treballs de camp | E56: =OFERTA!I61 -> 0 | F56: 61.64 | I56: jornades de camp
B57: Treballs de gabinet | E57: =OFERTA!I62 -> 5 | F57: 61.64 | I57: jornades de gabinet
B58: <<otros>>
B59: <<otros>>
B60: <<otros>>
B61: <<otros>>
B62: <<otros>>
B63: <<otros>>
B64: <<otros>>
B65: IMPORT TOTAL € | E65: =SUM(E55:E64) -> 5 | F65: =+E55*F55+E56*F56+E57*F57+E58*F58+E59*F59+E60*F60+E61*F61+E62*F62+E63*F63+E64*F64 -> 308.2

Sheet OFERTA
A1: PRESSUPOSTOS GEOTÈCCNICS
A2: CONCEPTE | B2: UNITATS | C2: PREU UNIT | D2: TOTAL | G2: SUBCONTRATACION SONDEOS
A3: SONDEIGS | G3: TPS
A4: P.A. Transporte equipos y personal | C4: 400 | D4: =(B4*C4) -> 0 | G4: 375 | H4: =B4*G4 -> 0 | I4: DESPLAZAMIENTO
A5: Emplaçament entre punts | C5: 51 | D5: =+B5*C5 -> 0 | G5: 50 | H5: =G5*B5 -> 0 | I5: Emplaçament entre punts
A6: ml de perforació en sòls fins a 20 m | C6: 43.41 | D6: =+B6*C6 -> 0 | G6: 38.41 | H6: =G6*B6 -> 0 | I6: ml de sòls fins a 20 m
A7: ml en roca tova fins a 20 m | C7: 51 | D7: =+B7*C7 -> 0 | G7: 46.09 | H7: =G7*B7 -> 0 | I7: ml de roques toves fins a 20 m
A8: ml en graves fins a 20 m | C8: 78 | D8: =+B8*C8 -> 0 | G8: 69 | H8: =G8*B8 -> 0 | I8: ml graves fins a 20 m
A9: ml en roca dura fins a 20 m | C9: 78 | D9: =+B9*C9 -> 0 | G9: 69 | H9: =G9*B9 -> 0 | I9: ml roca dura fins a 20 m
A10: ml de sòls fins de 20 a 40m | C10: =C6*1.2 -> 52.092 | D10: =+B10*C10 -> 0 | G10: =G6*1.2 -> 46.092 | H10: =G10*B10 -> 0 | I10: ml de sòls fins de 20 a 40m
A11: ml de roques toves de 20 a 40 m | C11: =C7*1.2 -> 61.2 | D11: =+B11*C11 -> 0 | G11: =G7*1.2 -> 55.308 | H11: =G11*B11 -> 0 | I11: ml de roques toves de 20 a 40 m
A12: ml de piezòmetre | C12: 18 | D12: =+B12*C12 -> 0 | G12: 12 | H12: =G12*B12 -> 0 | I12: ml piezometre
A13: Assaig Lefranc de permeabilitat | C13: 140 | D13: =+B13*C13 -> 0 | G13: 120 | H13: =G13*B13 -> 0 | I13: LEFRANC
A14: Assaig SPT | C14: 23 | D14: =+B14*C14 -> 0 | G14: 20.25 | H14: =G14*B14 -> 0 | I14: Assaig SPT
A15: mostra inalterada | C15: 23 | D15: =+B15*C15 -> 0 | G15: 21.25 | H15: =G15*B15 -> 0 | I15: mi
A16: caixa portatestimonis | C16: 12 | D16: =+B16*C16 -> 0 | G16: 9 | H16: =G16*B16 -> 0 | I16: PRESIOMETRES
A17: PA d'aigua per a la perforació de nivells rocosos | C17: 200 | D17: =+B17*C17 -> 0 | G17: 300 | H17: =G17*B17 -> 0 | I17: PA d'aigua
B18: Subtotal (1) | D18: =SUM(D4:D17) -> 0 | G18: 100 | H18: =B20*G18 -> 100 | I18: Desplaçament màquina de penetració
A19: ASSAIGS DPSH | G19: 8.9 | H19: =(B21*7)*G19 -> 186.9 | I19: ml penetració dinàmica DPSH
A20: Desplaçament de màquina de penetració | B20: 1 | C20: 110 | D20: =(B20*C20) -> 110 | G20: 18 | H20: =G20*B22 -> 18 | I20: ml previs
A21: unitat de penetració dinàmica DPSH | B21: 3 | C21: 120 | D21: =(B21*C21) -> 360 | G21: 21 | H21: =B23*G21 -> 21 | I21: sot
A22: ml previ | B22: 1 | C22: 45 | D22: =(B22*C22) -> 45 | G22: 35 | I22: obertura de paviment
A23: spt | B23: 1 | C23: 23 | D23: =(B23*C23) -> 23 | G23: 100 | I23: Testimoni de ferm
B24: Subtotal (2) | D24: =SUM(D20:D23) -> 538 | H24: =SUM(H4:H23) -> 325.9
A25: ASSAIGS DE LABORATORI
A26: Obertura de mostra | B26: 1 | C26: 5.93 | D26: =+B26*C26 -> 5.93 | G26: SUBCONTRATACIÓN LABORATORI
A27: Analisi granulomètric per tamissat | C27: 26.08 | D27: =+B27*C27 -> 0 | G27: SOIL-ASSAIG
A28: assaig de Limits d'Atterberg | C28: 27.76 | D28: =+B28*C28 -> 0 | G28: 4.75 | H28: =G28*B26 -> 4.75 | I28: Obertura de mostra
A29: compressió simple | C29: 31.5 | D29: =+B29*C29 -> 0 | G29: 23.34 | H29: =G29*B27 -> 0 | I29: Analisi granulomètric per tamissat
A30: tall directe UU | C30: 58 | D30: =+B30*C30 -> 0 | G30: 25.9 | H30: =G30*B28 -> 0 | I30: assaig de Limits d'Atterberg
A31: tall directe CD | C31: 120.45 | D31: =+B31*C31 -> 0 | G31: 30 | H31: =G31*B29 -> 0 | I31: permeabilitat
A32: permeabilitat en cèl·lula de edòmetre | C32: 85 | D32: =+B32*C32 -> 0 | G32: 40 | H32: =G32*B30 -> 0 | I32: tall directe UU
A33: Densitat aparent | C33: 10.1 | D33: =+B33*C33 -> 0 | G33: 43.75 | H33: =G33*B31 -> 0 | I33: inflament lliure
A34: Humitat natural | C34: 8.1 | D34: =+B34*C34 -> 0 | G34: 46.46 | H34: =G34*B32 -> 0 | I34: Lambe
A35: contingut en sulfats | B35: 1 | C35: 35 | D35: =+B35*C35 -> 35 | G35: 9.05 | H35: =G35*B33 -> 0 | I35: Densitat aparent
A36: Agressiviitat de l'aigua | C36: 118 | D36: =+B36*C36 -> 0 | G36: 7.15 | H36: =G36*B34 -> 0 | I36: Humitat natural
A37: Agressivitat dels sòls | C37: 60.47 | D37: =+B37*C37 -> 0 | G37: 30.25 | H37: =G37*B35 -> 30.25 | I37: compressió simple en roca
B38: Subtotal (3) | D38: =SUM(D26:D37) -> 40.93 | G38: 118.12 | H38: =G38*B36 -> 0 | I38: Agressiviitat de l'aigua
A39: INFORMES | G39: 54.97 | H39: =G39*B37 -> 0 | I39: Agressivitat dels sòls
A40: Redacció i direcció de l'estudi geotècnic | C40: 450 | D40: =B40*C40 -> 0 | G40: 28.61 | H40: =G40*B79 -> 0 | I40: Continugt en matèria orgànica
A41: Supervisió, direcció de treballs de camp i testificació de materials | C41: 180 | D41: =B41*C41 -> 0 | G41: 27.35 | H41: =G41*B80 -> 0 | I41: Contingut en sals solubles
D42: =SUM(D40:D41) -> 0 | G42: 34.26 | H42: =G42*B81 -> 0 | I42: Contingut en guixos
B43: TOTAL (SIN I.V.A.) | D43: =D42+D38+D24+D18 -> 578.93 | G43: 40.99 | H43: =G43*B82 -> 0 | I43: Proctor Normal
G44: 53.31 | H44: =G44*B83 -> 0 | I44: Proctor Modificat
A45: PRESSUPOSTOS GEOTÈCCNICS C0-C1 | G45: 98.45 | H45: =G45*B84 -> 0 | I45: Assaig CBR
A46: CONCEPTE | B46: UNITATS | C46: PREU UNIT | D46: TOTAL | G46: 43.75 | H46: =G46*B85 -> 0 | I46: Inflament lliure
A47: ESTUDIS C0-C1 | G47: 46.46 | H47: =G47*B86 -> 0 | I47: Colpase en sòls
A48: Desplaçament màquina de penetració | C48: 100 | D48: =(B48*C48) -> 0 | G48: 120 | H48: =G48*B87 -> 0 | I48: Alcali-silice
A49: unitat de penetració dinàmica DPSH | B49: 3 | C49: 90 | D49: =(B49*C49) -> 270 | H49: =SUM(H28:H48) -> 35 | I49: total
A50: ML PREVI | B50: 1 | C50: 28 | D50: =(B50*C50) -> 28
A51: SPT | B51: 1 | C51: 28 | D51: =+B51*C51 -> 28 | G51: SUBCONTRATACIÓN CALICATES
D52: =D48+D49+D50+D51 -> 326
A53: SONDEIG A ROTAC IÓ | G53: 55 | H53: =G53*F53 -> 0 | I53: hores de retro
A54: Sondeig a rotació, inclòs desplaçament i SPT'S | C54: 400 | D54: =(B54*C54) -> 0 | G54: 120 | H54: =G54*F54 -> 0 | I54: permisos
A55: obertura paviment (45€/u) | C55: 45 | D55: =(B55*C55) -> 0 | H55: =H53+H54 -> 0 | I55: total
B56: Subtotal (2) | D56: =D54+D55 -> 0
A57: ASSAIGS DE LABORATORI
A58: PA ASSAIG C0-C1 | B58: 1 | C58: 60 | D58: =+B58*C58 -> 60
A59: PA ASSAIGS PATOLOGIES | C59: 120 | D59: =+B59*C59 -> 0 | J59: HORAS reals | O59: TOTAL
B60: Subtotal (3) | D60: =SUM(D58:D59) -> 60 | H60: DIAS | I60: HORAS | J60: ARIADNA | K60: LEIAN | L60: EVA
A61: INFORMES | G61: CAMP | H61: =I61/8 -> 0 | I61: =J61+K61+L61 -> 0
A62: Redacció, direcció de l'Estudi geotècnic | B62: 1 | C62: 309 | D62: =B62*C62 -> 309 | G62: INFORME | H62: =I62/8 -> 0.625 | I62: =J62+K62+L62 -> 5 | K62: 4 | L62: 1
A63: Organització i supervisió dels treballs de camp | B63: 1 | C63: 90 | D63: =B63*C63 -> 90 | G63: ACR | H63: 0 | I63: =(H63*7) -> 0
B64: Subtotal (4) | D64: =D62+D63 -> 399
B65: TOTAL (SIN I.V.A.) | D65: =D64+D60+D52+D56 -> 785 | E65: 840 | G65: km | H65: DESPLAZAMIENTO | I65: DINAR | J65: ESMORZAR | K65: SOPAR | L65: HOTEL
H66: =((G66*4)*0.09*1.8)*H61 -> 0 | I66: =H61*12 -> 0 | J66: =(3.5*0) -> 0 | K66: =(15*0) -> 0 | L66: 0
A68: VIALS | G68: PLAN COST | H68: OFERTA | I68: CAT'S | J68: RESY | K68: DESPLAZ. | L68: SUBCONT. | M68: TOTAL
A69: CONCEPTE | B69: UNITATS | C69: PREU UNIT | D69: TOTAL | G69: GEOTÈCNIC SO | H69: =D43 -> 578.93 | I69: =(I61+I62+I63)*61.4 -> 307 | J69: =(I66+J66+K66+L66) -> 0 | K69: =(H66) -> 0 | L69: =H49+H24 -> 360.9 | M69: =(I69+J69+K69+L69) -> 667.9
G70: GEO C0-C1 | H70: =E65 -> 840 | I70: =(I61+I62+I63)*61.4 -> 307 | J70: =I66+J66+K66+L66 -> 0 | K70: =H66 -> 0 | L70: =H24+H49+H55 -> 360.9 | M70: =SUM(I70:L70) -> 667.9
A71: calicates mecàniques (inclou testificació de cales) | C71: 200 | D71: =(B71*C71) -> 0 | G71: GEO CALES | H71: =D94 -> 0 | I71: =(I61+I62+I63)*61.4 -> 307 | J71: =I66+J66+K66+L66 -> 0 | K71: =H66 -> 0 | L71: =H49+H55+H24 -> 360.9 | M71: =SUM(I71:L71) -> 667.9
A72: equip de senyalització durant la realització de les cales | C72: 280 | D72: =+B72*C72 -> 0 | G72: GEO S+CA | H72: =D94+D43 -> 578.93 | I72: =(I61+I62+I63)*61.4 -> 307 | J72: =I66+J66+K66+L66 -> 0 | K72: =H66 -> 0 | L72: =H55+H49+H24 -> 360.9 | M72: =SUM(I72:L72) -> 667.9
A73: Deslpaçamento de técnic a obra,testificació | C73: 280 | D73: =+B73*C73 -> 0
B74: Subtotal (1) | D74: =SUM(D71:D73) -> 0
A75: ASSAIGS DE LABORATORI
A76: Obertura de mostra | C76: 5.93 | D76: =+B76*C76 -> 0 | G76: SONDEIGS | H76: ML PREVISTOS
A77: Analisi granulomètric per tamissat | C77: 26.08 | D77: =+B77*C77 -> 0
A78: assaig de Limits d'Atterberg | C78: 27.76 | D78: =+B78*C78 -> 0
A79: conting materia orgànica | C79: 38 | D79: =+B79*C79 -> 0
A80: Contingut en sals solubles | C80: 30.88 | D80: =+B80*C80 -> 0
A81: Contingut en guixos | C81: 36.75 | D81: =+B81*C81 -> 0
A82: Proctor Normal | C82: 43.92 | D82: =+B82*C82 -> 0
A83: Proctor Modificat | C83: 70 | D83: =+B83*C83 -> 0
A84: Assaig CBR | C84: 115 | D84: =+B84*C84 -> 0
A85: Inflament lliure | C85: 35 | D85: =+B85*C85 -> 0
A86: Colpase en sòls | C86: 50.78 | D86: =+B86*C86 -> 0
A87: Agressivitat del sòls segons CE21 | C87: 60.47 | D87: =+B87*C87 -> 0
B88: Subtotal (2) | D88: =SUM(D76:D87) -> 0
A89: INFORMES
A90: Direcció i redacció de l'Estudi geotècnic | C90: 380 | D90: =B90*C90 -> 0
A91: PA de gestio de documentació | C91: 90 | D91: =B91*C91 -> 0
A92: Mitja jornada de testificació de cales | C92: 200 | D92: =B92*C92 -> 0
B93: Subtotal (3) | D93: =SUM(D90:D92) -> 0
B94: TOTAL (SIN I.V.A.) | D94: =D93+D88+D74 -> 0

Sheet FACTURA M
A1: PRESSUPOSTOS GEOTÈCCNICS
A2: CONCEPTE | B2: UNITATS | C2: PREU UNIT | D2: TOTAL | G2: SUBCONTRATACION SONDEOS
A3: SONDEIGS | G3: TPS
A4: P.A. Transporte equipos y personal | C4: 510 | D4: =(B4*C4) -> 0 | G4: 450 | H4: =G4*B4 -> 0 | I4: DESPLAZAMIENTO
A5: Emplaçament entre punts | C5: 51 | D5: =+B5*C5 -> 0 | G5: 42 | H5: =G5*B5 -> 0 | I5: Emplaçament entre punts
A6: ml de sòls fins a 20 m | C6: 41.14 | D6: =+B6*C6 -> 0 | G6: 60 | H6: =G6*B6 -> 0 | I6: ml de sòls fins a 20 m
A7: ml de roques toves fins a 20 m | C7: 51 | D7: =+B7*C7 -> 0 | G7: 68.9 | H7: =G7*B7 -> 0 | I7: ml de roques toves fins a 20 m
A8: ml graves fins a 20 m | C8: 72.11 | D8: =+B8*C8 -> 0 | G8: 40.93 | H8: =G8*B8 -> 0 | I8: ml graves fins a 20 m
A9: ml roca dura fins a 20 m | C9: 68 | D9: =+B9*C9 -> 0 | G9: 61.73 | H9: =G9*B9 -> 0 | I9: ml roca dura fins a 20 m
A10: ml de sòls fins de 20 a 40m | C10: =C6*1.2 -> 49.368 | D10: =+B10*C10 -> 0 | G10: 66.03 | H10: =G10*B10 -> 0 | I10: ml de sòls fins de 20 a 40m
A11: ml de roques toves de 20 a 40 m | C11: =C7*1.2 -> 61.2 | D11: =+B11*C11 -> 0 | G11: 45 | H11: =G11*B11 -> 0 | I11: ml de roques toves de 20 a 40 m
A12: ml graves de 20 a 40 m | C12: =C8*1.2 -> 86.532 | D12: =+B12*C12 -> 0 | G12: 7.08 | H12: =G12*B12 -> 0 | I12: ml graves de 20 a 40 m
A13: ml roca dura de 20 a 40 m | C13: =C9*1.2 -> 81.6 | D13: =+B13*C13 -> 0 | G13: 11.13 | H13: =G13*B13 -> 0 | I13: ml roca dura de 20 a 40 m
A14: Assaig SPT | C14: 22 | D14: =+B14*C14 -> 0 | G14: 2.98 | H14: =G14*B14 -> 0 | I14: Assaig SPT
A15: Mostra inalterada | C15: 23 | D15: =+B15*C15 -> 0 | G15: 1.81 | H15: =G15*B15 -> 0 | I15: Mostra inalterada
A16: Mostra parafinada | C16: 12 | D16: =+B16*C16 -> 0 | G16: 51 | H16: =G16*B16 -> 0 | I16: Mostra parafinada
A17: Caixa de sondeigs | C17: 11 | D17: =+B17*C17 -> 0 | G17: 13 | H17: =G17*B17 -> 0 | I17: Caixa de sondeigs
B18: Subtotal (1) | D18: =SUM(D4:D17) -> 0 | G18: 12 | H18: =G18*B20 -> 0 | I18: Desplaçament màquina de penetració
A19: ASSAIGS DPSH | G19: 60 | H19: =G19*B21 -> 0 | I19: unitat de penetració dinàmica DPSH
A20: Desplaçament màquina de penetració | C20: 250 | D20: =(B20*C20) -> 0 | G20: 22 | H20: =G20*B22 -> 0 | I20: ml previa a l'assaig SPT
A21: unitat de penetració dinàmica DPSH | C21: 10 | D21: =(B21*C21) -> 0 | H21: =G21*B23 -> 0 | I21: SPT
A22: ml previa a l'assaig SPT | C22: 28 | D22: =(B22*C22) -> 0 | G22: 8 | H22: =B55 -> 1 | I22: Calicata manual
A23: SPT | C23: 28 | D23: =(B23*C23) -> 0 | G23: 28.5 | H23: =B73 -> 0 | I23: Testimoni de ferm
B24: Subtotal (2) | D24: =SUM(D20:D23) -> 0 | H24: =SUM(H4:H23) -> 1
A25: ASSAIGS DE LABORATORI
A26: Obertura de mostra | C26: 5.93 | D26: =+B26*C26 -> 0 | G26: SUBCONTRATACIÓN LABORATORI
A27: Analisi granulomètric per tamissat | C27: 26.08 | D27: =+B27*C27 -> 0
A28: assaig de Limits d'Atterberg | C28: 27.76 | D28: =+B28*C28 -> 0 | G28: 7.2 | H28: =G28*B26 -> 0 | I28: Obertura de mostra
A29: Compressió simple | C29: 37.1 | D29: =+B29*C29 -> 0 | G29: 2.7 | H29: =G29*B27 -> 0 | I29: Analisi granulomètric per tamissat
A30: tall directe UU | C30: 51.97 | D30: =+B30*C30 -> 0 | H30: =G30*B28 -> 0 | I30: assaig de Limits d'Atterberg
A31: Tall directe CD | C31: 120.45 | D31: =+B31*C31 -> 0 | G31: 27 | H31: =G31*B29 -> 0 | I31: Compressió simple
A32: Consolidació unidimensional | C32: 163.18 | D32: =+B32*C32 -> 0 | G32: 18 | H32: =G32*B30 -> 0 | I32: tall directe UU
A33: Densitat aparent | C33: 10.1 | D33: =+B33*C33 -> 0 | G33: 31.5 | H33: =G33*B31 -> 0 | I33: Tall directe CD
A34: Humitat natural | C34: 8.1 | D34: =+B34*C34 -> 0 | G34: 40.5 | H34: =G34*B32 -> 0 | I34: Consolidació unidimensional
A35: Continugt en sulfats | C35: 35 | D35: =+B35*C35 -> 0 | H35: =G35*B33 -> 0 | I35: Densitat aparent
A36: Agressiviitat de l'aigua | C36: 118 | D36: =+B36*C36 -> 0 | H36: =G36*B34 -> 0 | I36: Humitat natural
A37: Agressivitat dels sòls | C37: 60.47 | D37: =+B37*C37 -> 0 | G37: 31.5 | H37: =G37*B35 -> 0 | I37: Continugt en sulfats
B38: Subtotal (3) | D38: =SUM(D26:D37) -> 0 | G38: 151.2 | H38: =G38*B36 -> 0 | I38: Agressiviitat de l'aigua
A39: INFORMES | G39: 81 | H39: =G39*B37 -> 0 | I39: Agressivitat dels sòls
A40: Informe geotècnic | B40: 1 | C40: 1500 | D40: =B40*C40 -> 1500 | G40: 55 | H40: =G40*B79 -> 0 | I40: Continugt en matèria orgànica
A41: Supervisió de treballs de camp | B41: 1 | C41: 2100 | D41: =B41*C41 -> 2100 | H41: =G41*B80 -> 0 | I41: Contingut en sals solubles
B42: Subtotal (4) | D42: =SUM(D40:D41) -> 3600 | G42: 27 | H42: =G42*B81 -> 0 | I42: Contingut en guixos
B43: TOTAL (SIN I.V.A.) | D43: =D42+D38+D24+D18 -> 3600 | G43: 18 | H43: =G43*B82 -> 0 | I43: Proctor Normal
G44: 31.5 | H44: =G44*B83 -> 0 | I44: Proctor Modificat
A45: PRESSUPOSTOS GEOTÈCCNICS C0-C1 | G45: 40.5 | H45: =G45*B84 -> 0 | I45: Assaig CBR
A46: CONCEPTE | B46: UNITATS | C46: PREU UNIT | D46: TOTAL | G46: 31.5 | H46: =G46*B85 -> 0 | I46: Inflament lliure
A47: ESTUDIS C0-C1 | G47: 117 | H47: =G47*B86 -> 0 | I47: Colpase en sòls
A48: Desplaçament màquina de penetració | C48: 250 | D48: =(B48*C48) -> 0 | G48: 27 | H48: =G48*B87 -> 0 | I48: Alcali-silice
A49: unitat de penetració dinàmica DPSH | B49: 2 | C49: 90 | D49: =(B49*C49) -> 180 | H49: =SUM(H28:H48) -> 0 | I49: total
A50: ml previa a l'assaig SPT | C50: 28 | D50: =(B50*C50) -> 0
A51: SPT | C51: 28 | D51: =+B51*C51 -> 0 | G51: SUBCONTRATACIÓN CALICATES
B52: Subtotal (1) | D52: =SUM(D48:D51) -> 180
A53: SONDEIG A ROTAC IÓ | G53: 49 | H53: =G53*B51 -> 0 | I53: hores de retro
A54: Sondeig a rotació, inclòs desplaçament i SPT'S | B54: 1 | C54: 400 | D54: =(B54*C54) -> 400 | G54: 120 | I54: permisos
A55: Cales manuals | B55: 1 | C55: 280 | D55: =(B55*C55) -> 280 | H55: =SUM(H53:H54) -> 0 | I55: total
B56: Subtotal (2) | D56: =D54+D55 -> 680
A57: ASSAIGS DE LABORATORI
A58: PA ASSAIG C0-C1 | B58: 1 | C58: 50 | D58: =+B58*C58 -> 50 | J58: HORAS CAT'S
A59: PA ASSAIGS PATOLOGIES (Inclou Lambe si cal) | C59: 120 | D59: =+B59*C59 -> 0 | H59: DIAS | I59: HORAS | J59: TAMARA | K59: ANNA | L59: QUIM | O59: TOTAL
B60: Subtotal (3) | D60: =SUM(D58:D59) -> 50 | G60: CAMPO | H60: 3 | I60: =SUM(J60:N60) -> 16.5 | K60: 14.5 | L60: 2
A61: INFORMES | G61: INFORME | H61: 3 | I61: =(H61*7) -> 21
A62: Informe geotècnic | B62: 1 | C62: 300 | D62: =B62*C62 -> 300 | G62: ACR | H62: 0 | I62: =(H62*7) -> 0
A63: Supervisió de treballs de camp | B63: 0 | C63: 90 | D63: =B63*C63 -> 0
B64: Subtotal (4) | D64: =D62+D63 -> 300 | H64: DESPLAZAMIENTO | I64: DINAR | J64: ESMORZA | K64: SOPAR | L64: HOTEL
B65: TOTAL (SIN I.V.A.) | D65: =D64+D60+D56+D52 -> 1210 | H65: =((100*2)*0.09*1.8)*H60 -> 97.2 | I65: =28.7+14.35 -> 43.05 | J65: =(3.5*0) -> 0 | K65: =(15*0) -> 0 | L65: =(60*0) -> 0
G67: PLAN COST | H67: OFERTA | I67: CAT'S | J67: RESY | K67: DESPLAZ. | L67: SUBCONT. | M67: TOTAL
A68: CALES | G68: GEOTÈCNIC SO | H68: =D43 -> 3600 | I68: =(I60+I61+I62)*61.4 -> 2302.5 | J68: =(I65+J65+K65+L65) -> 43.05 | K68: =(H65) -> 97.2 | L68: =H55+H49+H24 -> 1 | M68: =(I68+J68+K68+L68) -> 2443.75
A69: CONCEPTE | B69: UNITATS | C69: PREU UNIT | D69: TOTAL | G69: GEO C0-C1 | H69: =D65 -> 1210 | I69: =(I60+I61+I62)*61.4 -> 2302.5 | J69: =I65 -> 43.05 | K69: =H65 -> 97.2 | L69: =H24+H49+H55 -> 1 | M69: =SUM(I69:L69) -> 2443.75
G70: GEO CALES | H70: =D93 -> 3681 | I70: =(I60+I61+I62)*61.4 -> 2302.5 | J70: =I65+J65+K65+L65 -> 43.05 | K70: =H65 -> 97.2 | L70: =H55+H49+H24 -> 1 | M70: =SUM(I70:L70) -> 2443.75
A71: Calicates mecàniques | B71: 1 | C71: 51 | D71: =(B71*C71) -> 51 | G71: GEO S+CA | H71: =D93+D43 -> 7281 | I71: =(I60+I61+I62)*61.4 -> 2302.5 | J71: =I65+J65+K65+L65 -> 43.05 | K71: =H65 -> 97.2 | L71: =H24+H49+H55 -> 1 | M71: =SUM(I71:L71) -> 2443.75
A72: Recollida de mostres | B72: 1 | C72: 30 | D72: =+B72*C72 -> 30
A73: Testimonis de ferm (inclou obertura i tapat de l'obertura) | C73: 180 | D73: =+B73*C73 -> 0
B74: Subtotal (1) | D74: =SUM(D71:D73) -> 81
A75: ASSAIGS DE LABORATORI
A76: Obertura de mostra | C76: 5.93 | D76: =+B76*C76 -> 0
A77: Analisi granulomètric per tamissat | C77: 26.08 | D77: =+B77*C77 -> 0
A78: assaig de Limits d'Atterberg | C78: 27.76 | D78: =+B78*C78 -> 0
A79: Continugt en matèria orgànica | C79: 30.65 | D79: =+B79*C79 -> 0
A80: Contingut en sals solubles | C80: 30.88 | D80: =+B80*C80 -> 0
A81: Contingut en guixos | C81: 36.75 | D81: =+B81*C81 -> 0
A82: Proctor Normal | C82: 43.92 | D82: =+B82*C82 -> 0
A83: Proctor Modificat | C83: 70 | D83: =+B83*C83 -> 0
A84: Assaig CBR | C84: 115 | D84: =+B84*C84 -> 0
A85: Inflament lliure | C85: 35 | D85: =+B85*C85 -> 0
A86: Colpase en sòls | C86: 50.78 | D86: =+B86*C86 -> 0
A87: Alcali-silice | C87: 125 | D87: =+B87*C87 -> 0
B88: Subtotal (2) | D88: =SUM(D76:D87) -> 0
A89: INFORMES
A90: Informe geotècnic | B90: 1 | C90: 1500 | D90: =B90*C90 -> 1500
A91: testificació de treballs de camp | B91: 1 | C91: 2100 | D91: =B91*C91 -> 2100
B92: Subtotal (3) | D92: =SUM(D90:D91) -> 3600
B93: TOTAL (SIN I.V.A.) | D93: =D92+D88+D74 -> 3681

Sheet Material Cost (lab)
A1: material cost (lab) | B1: max. 40 Characters | C1: max. 80 Characters | D1: max. 40 Characters2 | E1: max. 80 Characters3
A2: T13-380-00-G100001 | B2: Apertura y descripción de muestra | C2: Apertura y descripción de muestra de suelo, roca y/o áridos | D2: Sample opening and description | E2: Opening and description of soil, rock and/or aggregate samples
A3: T13-380-00-G100002 | B3: Preparación muestras ensayos de suelos | C3: Preparación de muestras para ensayos de suelos UNE 103-100-95 | D3: Soil test sample preparation | E3: Sample preparation for soil tests UNE 103-100-95
A4: T13-380-00-G100003 | B4: Remoldeo de pastilla para ensayo | C4: Remoldeo pastilla ensayo edométrico o CD o colapso o hinchamiento libre | D4: Test tablet topping | E4: Edometric/CD/collapse/free swelling test tablet remoulding
A5: T13-380-00-G100004 | B5: Remoldeo de una probeta para ensayo | C5: Remoldeo probeta para rotura a CS o triaxial o permeabilidad de 1,5 pulgadas | D5: Swirling of a test specimen | E5: Remoulding of specimen for CS or triaxial breakage or 1.5 inch permeability
A6: T13-380-00-G100005 | B6: Tallado muestra recibida en bloque | C6: Tallado de muestra recibida en bloque parafinado | D6: Carving of a sample received as a block | E6: Carving of specimen received in paraffin block
A7: T13-380-00-G100006 | B7: Tallado de muestra de testigo de sondeo | C7: Tallado de muestra de testigo de sondeo | D7: Cutting of core samples | E7: Carving of core sample
A8: T13-380-00-G100007 | B8: Preparación fracciones-mezcla materiales | C8: Preparación fracciones-mezcla materiales granulares para ensayo de compactación | D8: Preparation of fractions-mixed materials | E8: Preparation of granular material mix-fractions for compaction test
A9: T13-380-00-G100008 | B9: Molido muestra salida de tamiz 0,080 UNE | C9: Molido de muestra con 60 g de salida de tamiz 0,080 UNE | D9: Grinding sample coming out 0.080UNEsieve | E9: Grinding of sample with 60 g output of 0.080 UNE sieve
A10: T13-380-00-G110001 | B10: Determinación humedad secado estufa | C10: Determinación de la humedad de un suelo mediante secado en estufa UNE 103-300-93 | D10: Moisture determination oven-drying | E10: Determination of the humidity of a soil by drying in an oven UNE 103-300-93
A11: T13-380-00-G110002 | B11: Determinación de la densidad de un suelo | C11: Determinación densidad suelo. Método de la balanza hidrostática UNE 103-301-94 | D11: Determination of the density of a soil | E11: Determination of soil density. Hydrostatic balance method UNE 103-301-94
A12: T13-380-00-G110003 | B12: Determinación Límites de Atterberg | C12: Determinación Límites de Atterberg UNE 103-103-94 y 103-104-93 | D12: Determination of Atterberg limits | E12: Determination of Atterberg Limits UNE 103-103-94 y 103-104-93
... A152: T13-720-00-G500004 | B152: Coeficiente de friabilidad de las arenas | C152: Coeficiente de friabilidad de las arenas. UNE 83-115-89. | D152: Coefficient of friability of the sands | E152: Coefficient of friability of sands. UNE 83-115-89.

Sheet Material Cost
A1: TS | B1: TS-Product | C1: sevice id | D1: Service | E1: Client/obt | F1: Text | G1: Description | H1: more detailed description | I1: SubCod | J1: Material CODES
A2: TS-1000 | B2: Environmental characterization studies | C2: S10 | D2: Accredited environmental inspections (ENAC) | E2: 380 | F2: Exploratory characterization studies. | G2: Exploratory characterization studies. | H2: Basic characterization studies of the potential contamination of the soil and associated groundwater. | I2: 10 | J2: S10-380-10 | L2: Exploratory characterization studies. | M2: S10-380-10
C3: S10 | E3: 380 | F3: Detailed characterization studies. | G3: Detailed characterization studies. | H3: Complete characterization studies of the potential contamination of the soil and associated groundwater, which delimits the extent of the contamination. | I3: 20 | J3: S10-380-20 | L3: Detailed characterization studies. | M3: S10-380-20
C4: S10 | E4: 725 | F4: Certification of the quality of the remaining soil. | G4: Certification of the quality of the remaining soil. | H4: Soil characterization studies during the excavation of a potentially contaminated plot. | I4: 10 | J4: S10-725-10 | L4: Certification of the quality of the remaining soil. | M4: S10-725-10
C5: S10 | E5: 551 | F5: Control and monitoring of groundwater quality. | G5: Control and monitoring of groundwater quality. | H5: Establishment of potential groundwater contamination | I5: 10 | J5: S10-551-10 | L5: Control and monitoring of groundwater quality. | M5: S10-551-10
C6: G60 | D6: Unaccredited environmental studies. | E6: 134 | F6: Environmental impact studies. | G6: Environmental impact studies. | H6: Carrying out environmental impact studies for the implementation of civil works or industrial sites. | I6: 10 | J6: G60-134-10 | L6: Environmental impact studies. | M6: G60-134-10
C7: G60 | E7: 134 | F7: Quantitative risk analysis. | G7: Quantitative risk analysis. | H7: Quantitative risk assessment studies to determine the maximum allowable concentrations of a given pollutant or establish cleanup targets levels for a site. | I7: ´00 | J7: G60-134-´00 | L7: Quantitative risk analysis. | M7: G60-134-´00
B8: Soil and groundwater remediation | C8: G60 | D8: Remediation work. | E8: 725 | F8: Soil remediation projects. | G8: Soil remediation projects. | H8: Drafting of soil and associated groundwater remediation projects that allow the cleanup objectives to be achieved at a specific site. | I8: 10 | J8: G60-725-10 | L8: Soil remediation projects. | M8: G60-725-10
C9: G60 | E9: 129 | F9: Remediation monitoring reports. | G9: Remediation monitoring reports. | H9: Drafting of technical reports to monitor the remediation process of a site. | I9: 10 | J9: G60-129-10 | L9: Remediation monitoring reports. | M9: G60-129-10
A10: TS-1202 | B10: Geotechnical characterization studies | C10: S51 | D10: Geotechnical studies. | E10: 733 | F10: Geotechnical studies. | G10: Geotechnical studies for building. | H10: Drafting of geotechnical reports associated with building works (bearing capacity of the spoil, settlements, geotechnical characterization, etc.). | I10: 09 | J10: S51-733-09 | L10: Geotechnical studies for building. | M10: S51-733-09
C11: S51 | E11: 733 | G11: Slope stability studies. | H11: Geotechnical studies to characterize the stability of slopes in civil works (roads) or buildings (excavation holes for basements). | I11: 10 | J11: S51-733-10 | L11: Slope stability studies. | M11: S51-733-10
C12: S51 | E12: 733 | G12: Geotechnical studies of linear works (roads, gas pipelines, etc.) | H12: Geotechnical studies for the construction of linear works (establishing the degree of excavability and stability of the terrain, description of geotechnical problems, etc.). | I12: 20 | J12: S51-733-20 | L12: Geotechnical studies of linear works (roads, gas pipelines, etc.) | M12: S51-733-20
C13: T13 | D13: Laboratory tests of soil, rocks, agrregates, water and others. | E13: 380 | F13: Laboratory tests of soil, rocks, agrregates, water and others. | G13: #1 Laboratory tests on soil samples. | H13: Performance of physicochemical characterization tests, resistance, deformability, etc. In soil mechanics. | I13: 00 | J13: T13-380-00 | K13: +Subitems | L13: #1 Laboratory tests on soil samples. | M13: T13-380-00
C14: T13 | E14: 733 | G14: #2 Laboratory tests on rock samples. | H14: Performance of physicochemical characterization tests, resistance, deformability, etc. In rock mechanics. | I14: 00 | J14: T13-733-00 | L14: #2 Laboratory tests on rock samples. | M14: T13-733-00
C15: T13 | E15: 529 | G15: #3 Laboratory tests on aggregates samples. | H15: Performance of physicochemical characterization tests, resistance, deformability, etc. In aggregares. | I15: 00 | J15: T13-529-00 | L15: #3 Laboratory tests on aggregates samples. | M15: T13-529-00
C16: T13 | E16: 551 | G16: #4 Laboratory tests on water samples. | H16: Chemical characterization tests in water. | I16: 00 | J16: T13-551-00 | L16: #4 Laboratory tests on water samples. | M16: T13-551-00
C17: T13 | E17: 720 | G17: #5 Others laboratory tests. | H17: Others laboratory test (new test). | I17: 00 | J17: T13-720-00 | L17: #5 Others laboratory tests. | M17: T13-720-00
B19: Subcod 00 y/o 10 (00 = at home; 10= at the customer's site).

Sheet Cost Center
A1: Activity | B1: PtCtr
A2: Laboratory & Geothechnics studies | B2: 15803173
A3: Contaminated soils | B3: 15804173
A4: Remediation | B4: 15805173
A5: Cataluña | B5: 15806173

Sheet Technicians
A1: Técnicos
A2: Eva Vázquez Marcet
A3: Ariadna Salla
A4: Leian Martin
